utterless/__init__.py
utterless/__main__.py
utterless/main.py
utterless/results.py
utterless/runner.py
utterless/contrib/__init__.py
utterless/contrib/django.py
utterless-0.4.2.dist-info/LICENCE.txt
utterless-0.4.2.dist-info/METADATA
utterless-0.4.2.dist-info/WHEEL
utterless-0.4.2.dist-info/top_level.txt
utterless-0.4.2.dist-info/RECORD
