Metadata-Version: 2.1
Name: utterless
Version: 0.4.2
Summary: Extend Python's "unittest" to better handle "logging" messages
Home-page: https://github.com/pscl4rke/utterless
Author: P. S. Clarke
Author-email: utterless@pscl4rke.net
Project-URL: Source Code, https://github.com/pscl4rke/utterless
Project-URL: Issues, https://github.com/pscl4rke/utterless/issues
Project-URL: Licence, https://github.com/pscl4rke/utterless/blob/master/LICENCE.txt
Classifier: Development Status :: 4 - Beta
Classifier: Environment :: Console
Classifier: Intended Audience :: Developers
Classifier: Topic :: Software Development :: Debuggers
Classifier: Topic :: Software Development :: Testing
Classifier: Topic :: Software Development :: Testing :: Unit
Classifier: Topic :: System :: Logging
Classifier: Topic :: Utilities
License-File: LICENCE.txt
